psym/__init__.py
psym/_utils.py
psym/client.py
psym/config.py
psym/exceptions.py
psym/survey_schema.json
psym/api/__init__.py
psym/api/_flow.py
psym/api/alarm_status.py
psym/api/comparator.py
psym/api/counter.py
psym/api/counter_family.py
psym/api/counter_formula.py
psym/api/customer.py
psym/api/document_category.py
psym/api/domain.py
psym/api/equipment.py
psym/api/equipment_type.py
psym/api/event_severity.py
psym/api/features.py
psym/api/file.py
psym/api/formula.py
psym/api/kpi.py
psym/api/kpi_category.py
psym/api/kqi_category.py
psym/api/kqi_perspective.py
psym/api/kqi_source.py
psym/api/kqi_temporal_frecuency.py
psym/api/link.py
psym/api/location.py
psym/api/location_template.py
psym/api/location_type.py
psym/api/network_type.py
psym/api/organization.py
psym/api/port.py
psym/api/port_type.py
psym/api/project.py
psym/api/project_type.py
psym/api/property_type.py
psym/api/recommendation_category.py
psym/api/recommendation_sources.py
psym/api/recommendations.py
psym/api/resource_specification.py
psym/api/resource_specification_items.py
psym/api/resource_specification_relationship.py
psym/api/resource_type.py
psym/api/resource_type_relationship.py
psym/api/rule.py
psym/api/rule_limit.py
psym/api/rule_type.py
psym/api/service.py
psym/api/service_type.py
psym/api/site_survey.py
psym/api/site_survey_schema.py
psym/api/tech.py
psym/api/threshold.py
psym/api/user.py
psym/api/vendor.py
psym/api/work_order.py
psym/api/work_order_type.py
psym/common/__init__.py
psym/common/cache.py
psym/common/constant.py
psym/common/data_class.py
psym/common/data_enum.py
psym/common/data_format.py
psym/common/endpoint.py
psym/graphql/__init__.py
psym/graphql/enum/__init__.py
psym/graphql/enum/action_type_id.py
psym/graphql/enum/alarm_status_filter_type.py
psym/graphql/enum/alarm_status_order_field.py
psym/graphql/enum/cellular_network_type.py
psym/graphql/enum/check_list_item_enum_selection_mode.py
psym/graphql/enum/check_list_item_type.py
psym/graphql/enum/comparator_filter_type.py
psym_TEST-2.5.31.dist-info/LICENSE
psym_TEST-2.5.31.dist-info/METADATA
psym_TEST-2.5.31.dist-info/WHEEL
psym_TEST-2.5.31.dist-info/top_level.txt
psym_TEST-2.5.31.dist-info/RECORD
